xspf_lib-0.3.4.dist-info/METADATA
xspf_lib-0.3.4.dist-info/WHEEL
xspf_lib-0.3.4.dist-info/licenses/LICENSE
xspf_lib/__init__.py
xspf_lib/_version.py
xspf_lib/base.py
xspf_lib/builders.py
xspf_lib/constants.py
xspf_lib/elements.py
xspf_lib/parsers.py
xspf_lib/types.py
xspf_lib/utils.py
xspf_lib-0.3.4.dist-info/RECORD
