Metadata-Version: 2.1
Name: xspf-lib
Version: 0.3.4
Summary: Library for work with xspf format
Keywords: xspf playlist
Author-Email: Dzmitry Izaitka <dem214overlord@gmail.com>
License: MIT
Classifier: License :: OSI Approved :: MIT License
Classifier: Operating System :: OS Independent
Classifier: Programming Language :: Python :: 3
Classifier: Topic :: Multimedia :: Sound/Audio
Classifier: Topic :: Multimedia :: Video
Classifier: Topic :: Software Development :: Libraries :: Python Modules
Project-URL: Source, https://github.com/dem214/xspf-lib
Project-URL: Bug tracker, https://github.com/dem214/xspf-lib/issues
Project-URL: Documentation, https://xspf-lib.readthedocs.io/
Requires-Python: >=3.7
